wikibot3rd/__init__.py
wikibot3rd/crypt.py
wikibot3rd/mwTable.py
wikibot3rd/pagehistory.py
wikibot3rd/selector.py
wikibot3rd/smw.py
wikibot3rd/sso.py
wikibot3rd/sso_users.py
wikibot3rd/version.py
wikibot3rd/wiki.py
wikibot3rd/wikiaction.py
wikibot3rd/wikibackup.py
wikibot3rd/wikibot.py
wikibot3rd/wikiclient.py
wikibot3rd/wikiedit.py
wikibot3rd/wikinuke.py
wikibot3rd/wikipush.py
wikibot3rd/wikiquery.py
wikibot3rd/wikirestore.py
wikibot3rd/wikitext.py
wikibot3rd/wikiupload.py
wikibot3rd/wikiuser.py
wikibot3rd/wikiuser_cmd.py
wikibot3rd_examples/__init__.py
wikibot3rd_examples/queries.yaml
py_3rdparty_mediawiki-0.17.0.dist-info/METADATA
py_3rdparty_mediawiki-0.17.0.dist-info/WHEEL
py_3rdparty_mediawiki-0.17.0.dist-info/entry_points.txt
py_3rdparty_mediawiki-0.17.0.dist-info/licenses/LICENSE
py_3rdparty_mediawiki-0.17.0.dist-info/RECORD
