Metadata-Version: 2.4
Name: py-3rdparty-mediawiki
Version: 0.17.0
Summary: Wrapper for mwclient with improvements for 3rd party wikis
Project-URL: homepage, https://wiki.bitplan.com/index.php/Py-3rdparty-mediawiki
Project-URL: documentation, https://wiki.bitplan.com/index.php/Py-3rdparty-mediawiki
Project-URL: repository, https://wiki.bitplan.com/index.php/Py-3rdparty-mediawiki
Author-email: Wolfgang Fahl <wf@bitplan.com>, Tim Holzheim <tim.holzheim@rwth-aachen.de>
Maintainer-email: Wolfgang Fahl <wf@bitplan.com>, Tim Holzheim <tim.holzheim@rwth-aachen.de>
License-Expression: Apache-2.0
License-File: LICENSE
Classifier: Development Status :: 5 - Production/Stable
Classifier: Environment :: Web Environment
Classifier: Intended Audience :: Developers
Classifier: License :: OSI Approved :: Apache Software License
Classifier: Operating System :: OS Independent
Classifier: Programming Language :: Python :: 3 :: Only
Classifier: Programming Language :: Python :: 3.10
Classifier: Programming Language :: Python :: 3.11
Classifier: Programming Language :: Python :: 3.12
Classifier: Programming Language :: Python :: 3.13
Classifier: Topic :: Software Development :: Libraries :: Python Modules
Requires-Python: >=3.10
Requires-Dist: bcrypt>=4.3.0
Requires-Dist: gitpython
Requires-Dist: jinja2
Requires-Dist: mwclient>=0.11.0
Requires-Dist: mwparserfromhell>=0.7.2
Requires-Dist: mysql-connector-python>=9.4.0
Requires-Dist: pybasemkit>=0.0.5
Requires-Dist: pycryptodome>=3.20.0
Requires-Dist: pylodstorage>=0.17.0
Requires-Dist: pywikibot>=8.2
Requires-Dist: shutup>=0.2.0
Requires-Dist: tqdm>=4.67.1
Requires-Dist: wikitextparser>=0.56.4
Provides-Extra: test
Requires-Dist: green; extra == 'test'
